odoo/addons/shopinvader_sale_profile_update_price/README.rst
odoo/addons/shopinvader_sale_profile_update_price/__init__.py
odoo/addons/shopinvader_sale_profile_update_price/__manifest__.py
odoo/addons/shopinvader_sale_profile_update_price/i18n/shopinvader_sale_profile_update_price.pot
odoo/addons/shopinvader_sale_profile_update_price/models/__init__.py
odoo/addons/shopinvader_sale_profile_update_price/models/sale_order.py
odoo/addons/shopinvader_sale_profile_update_price/readme/CONTRIBUTORS.rst
odoo/addons/shopinvader_sale_profile_update_price/readme/DESCRIPTION.rst
odoo/addons/shopinvader_sale_profile_update_price/static/description/index.html
odoo/addons/shopinvader_sale_profile_update_price/tests/__init__.py
odoo/addons/shopinvader_sale_profile_update_price/tests/test_shopinvader_sale_price_update.py
odoo14_addon_shopinvader_sale_profile_update_price-14.0.1.0.1.dist-info/METADATA
odoo14_addon_shopinvader_sale_profile_update_price-14.0.1.0.1.dist-info/WHEEL
odoo14_addon_shopinvader_sale_profile_update_price-14.0.1.0.1.dist-info/top_level.txt
odoo14_addon_shopinvader_sale_profile_update_price-14.0.1.0.1.dist-info/RECORD
