Metadata-Version: 2.1
Name: odoo14-addon-shopinvader-sale-profile-update-price
Version: 14.0.1.0.1
Summary: Triggers the sale order price computation without remove sale profile's pricelist
Home-page: https://github.com/shopinvader/odoo-shopinvader
Author: ACSONE SA/NV
License: AGPL-3
Platform: UNKNOWN
Classifier: Programming Language :: Python
Classifier: Framework :: Odoo
Classifier: Framework :: Odoo :: 14.0
Classifier: License :: OSI Approved :: GNU Affero General Public License v3
Requires-Python: >=3.6
Requires-Dist: odoo14-addon-shopinvader-sale-profile
Requires-Dist: odoo14-addon-shopinvader-sale-update-price
Requires-Dist: odoo (<14.1dev,>=14.0a)
